README.txt
setup.py
van_api.py
van_api.egg-info/PKG-INFO
van_api.egg-info/SOURCES.txt
van_api.egg-info/dependency_links.txt
van_api.egg-info/requires.txt
van_api.egg-info/top_level.txt